MANIFEST.in
README.rst
setup.py
PlopRotTemp/PlopRotTemp.py
PlopRotTemp/__init__.py
PlopRotTemp/main.py
PlopRotTemp.egg-info/PKG-INFO
PlopRotTemp.egg-info/SOURCES.txt
PlopRotTemp.egg-info/dependency_links.txt
PlopRotTemp.egg-info/top_level.txt
PlopRotTemp/Utilities/__init__.py
PlopRotTemp/Utilities/non_standard_res.py
PlopRotTemp/param/f14_sgbnp.param
PlopRotTemp/param/params.cov
PlopRotTemp/param/params.nb
PlopRotTemp/param/sgbnp.param
PlopRotTemp/param/similarity.param
PlopRotTemp/template/__init__.py
PlopRotTemp/template/chargeHandler.py
PlopRotTemp/template/templateBuilder.py
PlopRotTemp/template/tmp_helpers.py