Metadata-Version: 1.0
Name: PlopRotTemp
Version: 1.0.0
Summary: Extract forcefield parameters of a small molecule using OPLS2005
Home-page: https://github.com/NostrumBioDiscovery/PlopRotTemp
Author: Daniel Soler
Author-email: daniel.soler@nostrumbiodiscovery.com
License: UNKNOWN
Platform: UNKNOWN
